grip_intros/__init__.py
grip_intros/base.py
grip_intros/client.py
grip_intros/container.py
grip_intros/thing.py
grip_intros/version.py
grip_intros-0.1.3.dist-info/AUTHORS
grip_intros-0.1.3.dist-info/LICENCE.txt
grip_intros-0.1.3.dist-info/METADATA
grip_intros-0.1.3.dist-info/WHEEL
grip_intros-0.1.3.dist-info/top_level.txt
grip_intros-0.1.3.dist-info/RECORD
