Metadata-Version: 2.1
Name: grip-intros
Version: 0.1.3
Summary: Python client for GRIP meetings API
Home-page: https://github.com/crowdcomms/grip-python
Author: Ben Harling
Author-email: bharling@crowdcomms.co.uk
License: MIT
Keywords: grip client meetings connections things api
Platform: UNKNOWN
Classifier: Development Status :: 2 - Pre-Alpha
Classifier: Intended Audience :: Developers
Classifier: Topic :: Software Development :: Libraries :: Python Modules
Classifier: License :: OSI Approved :: MIT License
Classifier: Programming Language :: Python :: 3.3
Classifier: Programming Language :: Python :: 3.4
Classifier: Programming Language :: Python :: 3.5
Classifier: Programming Language :: Python :: 3.6
Requires-Dist: requests (<3)
Provides-Extra: dev
Provides-Extra: test
Requires-Dist: pytest (==3.0.4) ; extra == 'test'
Requires-Dist: pytest-cov (==2.4.0) ; extra == 'test'
Requires-Dist: pytest-pep8 (==1.0.6) ; extra == 'test'
Requires-Dist: responses (==0.5.1) ; extra == 'test'
